aleister/__init__.py
aleister/question/__init__.py
aleister/question/base.py
aleister/question/choice.py
aleister/question/message.py
aleister/question/text.py
aleister/question/yesno.py
aleister/wizard.py
aleister-0.1.1.dist-info/WHEEL
aleister-0.1.1.dist-info/METADATA
aleister-0.1.1.dist-info/RECORD
