Metadata-Version: 2.1
Name: aleister
Version: 0.1.1
Summary: library for CUI wizard
License: MIT
Author: Hirotomo Moriwaki
Author-email: philopon.dependence@gmail.com
Requires-Python: >=3.5,<4.0
Classifier: License :: OSI Approved :: MIT License
Classifier: Programming Language :: Python :: 3
Classifier: Programming Language :: Python :: 3.5
Classifier: Programming Language :: Python :: 3.6
Classifier: Programming Language :: Python :: 3.7
Requires-Dist: prompt_toolkit (>=2.0,<3.0)
